d_prob.v
// d_prob.v - 用于计算 Type II 反馈概率 d（含修复后的完整实现）

module d_prob #(
    parameter T_WIDTH = 8                       // 超参数 T 的位宽
)(
    input clk,
    input rst_n,

    input [T_WIDTH:0] T,                        // 超参数 T，例如 36
    input [T_WIDTH:0] q,                        // 目标类别 q（1 表正样本，0 表负样本）
    input signed [T_WIDTH:0] v,                 // 当前类别得分（有符号数）

    output reg [T_WIDTH-1:0] d                  // 输出概率值 d（用于与 rand 比较）
);

    // ===================== 原理说明 =====================
    // Tsetlin 反馈中 Type II 的概率计算：
    //   d = | ±T - clip(v) | / 2
    // clip(v)：将 v 限制在 [-T, T] 范围
    // error = T-clip(v) 或 -T-clip(v)
    // d = abs(error) >> 1

    wire signed [T_WIDTH:0] clipped_v;         // 裁剪后的 v
    wire signed [T_WIDTH:0] error_val;         // 误差值
    reg [T_WIDTH-1:0] abs_error;               // 绝对值后再右移1位作为 d

    // clip(v, T)：将 v 限制在 [-T, T]
    assign clipped_v = (v > $signed(T)) ? $signed(T) :
                       (v < -$signed(T)) ? -$signed(T) : v;

    // error_val = (q==1) ? (T - clip(v)) : (-T - clip(v))
    assign error_val = q ? ($signed(T) - clipped_v) : (-$signed(T) - clipped_v);

    // 用时序逻辑先计算 abs(error)，再除以2，避免阻塞赋值冲突
    always @(posedge clk or negedge rst_n) begin
        if (!rst_n) begin
            abs_error <= 0;
            d <= 0;
        end else begin
            abs_error <= (error_val < 0) ? -error_val[T_WIDTH-1:0] : error_val[T_WIDTH-1:0];
            d <= abs_error >> 1;  // 相当于 /2
        end
    end
endmodule

d_prob_tb.v
// d_prob_tb.v - 测试 d_prob 模块的功能与正确性（含 PASS/ERROR 检查输出）

module d_prob_tb;
    parameter T_WIDTH = 8;

    reg clk, rst_n;
    reg  [T_WIDTH:0] T, q;
    reg signed [T_WIDTH:0] v;
    wire [T_WIDTH-1:0] d;

    // 实例化模块
    d_prob #( .T_WIDTH(T_WIDTH) ) uut (
        .clk(clk),
        .rst_n(rst_n),
        .T(T),
        .q(q),
        .v(v),
        .d(d)
    );

    // 时钟生成
    always #5 clk = ~clk;

    // 结果检查任务
    task check;
        input [7:0] test_id;
        input [T_WIDTH-1:0] expected;
        begin
            if (d === expected)
                $display("[PASS] Test %0d: d = %0d", test_id, d);
            else
                $display("[ERROR] Test %0d: d = %0d, expect = %0d", test_id, d, expected);
        end
    endtask

    initial begin
        $dumpfile("d_prob.vcd");
        $dumpvars(0, d_prob_tb);

        clk = 0;
        rst_n = 0;
        T = 36;
        #10 rst_n = 1;

        // === 测试用例：q 表目标类别，v 表预测得分 ===
        q = 0; v = 20;   #20 check(1, 28); // | -36 - 20 | = 56 >> 1 = 28
        q = 1; v = 0;    #20 check(2, 18); // | 36 - 0 | = 36 >> 1 = 18
        q = 1; v = 50;   #20 check(3, 0);  // clipped to 36 => d = 0
        q = 0; v = -60;  #20 check(4, 0);  // clipped to -36 => d = 0
        q = 0; v = -20;  #20 check(5, 8);  // | -36 - (-20) | = 16 >> 1 = 8

        #20 $finish;
    end
endmodule

d_prob.vcd
$date
	Wed Jun  4 00:41:15 2025
$end
$version
	Icarus Verilog
$end
$timescale
	1s
$end
$scope module d_prob_tb $end
$var wire 8 ! d [7:0] $end
$var parameter 32 " T_WIDTH $end
$var reg 9 # T [8:0] $end
$var reg 1 $ clk $end
$var reg 9 % q [8:0] $end
$var reg 1 & rst_n $end
$var reg 9 ' v [8:0] $end
$scope module uut $end
$var wire 9 ( T [8:0] $end
$var wire 1 $ clk $end
$var wire 9 ) q [8:0] $end
$var wire 1 & rst_n $end
$var wire 9 * v [8:0] $end
$var wire 9 + error_val [8:0] $end
$var wire 9 , clipped_v [8:0] $end
$var parameter 32 - T_WIDTH $end
$var reg 8 . abs_error [7:0] $end
$var reg 8 / d [7:0] $end
$upscope $end
$scope task check $end
$var reg 8 0 expected [7:0] $end
$var reg 8 1 test_id [7:0] $end
$upscope $end
$upscope $end
$enddefinitions $end
$comment Show the parameter values. $end
$dumpall
b1000 -
b1000 "
$end
#0
$dumpvars
bx 1
bx 0
b0 /
b0 .
bx ,
bx +
bx *
bx )
b100100 (
bx '
0&
bx %
0$
b100100 #
b0 !
$end
#5
1$
#10
b111001000 +
b10100 ,
0$
b10100 '
b10100 *
b0 %
b0 )
1&
#15
b111000 .
1$
#20
0$
#25
b11100 !
b11100 /
1$
#30
b0 ,
b100100 +
0$
b0 '
b0 *
b1 %
b1 )
b11100 0
b1 1
#35
b100100 .
1$
#40
0$
#45
b10010 !
b10010 /
1$
#50
b0 +
b100100 ,
0$
b110010 '
b110010 *
b10010 0
b10 1
#55
b0 .
1$
#60
0$
#65
b0 !
b0 /
1$
#70
b111011100 ,
b0 +
0$
b111000100 '
b111000100 *
b0 %
b0 )
b0 0
b11 1
#75
1$
#80
0$
#85
1$
#90
b111110000 +
b111101100 ,
0$
b111101100 '
b111101100 *
b100 1
#95
b10000 .
1$
#100
0$
#105
b1000 !
b1000 /
1$
#110
0$
b1000 0
b101 1
